{
  "id": 1787,
  "name": "Forex Funded Trader",
  "slug": "forex-funded-trader",
  "logo": "/logos/forex-funded-trader.png",
  "rating": 7,
  "reviews": "prop-firm audit",
  "type": "prop-firm",
  "description": "Comprehensive prop-firm forensic dossier based on legacy research archives.",
  "fullReview": "# Forex Funded Trader — EXTENSIVE PROP FIRM DEEP-DIVE REPORT\n\n**Report Date:** April 2, 2026\n**Target:** Forex Funded Trader\n**Report Type:** Deep-Dive — Prop Firm Analysis\n**Data Sources:** Official website, Trustpilot, industry review platforms, community forums\n\n---\n\n## 1. COMPANY DEEP DIVE\n\n### Founding & History\n\nForex Funded Trader positions itself as a forex-specialist prop firm, focusing specifically on currency trading rather than offering a broad multi-asset platform. This specialization reflects a strategic decision to serve the largest segment of retail traders — those primarily focused on forex markets.\n\nThe company was founded during the prop firm expansion era (2022-2024), entering a market that already had numerous generalist prop firms. The founders identified that many forex traders prefer focused platforms that understand their specific needs, instruments, and trading styles. By specializing in forex, Forex Funded Trader aims to provide a more tailored experience.\n\nThe founding team recognized that while multi-asset platforms offer breadth, forex-focused traders often have specific requirements around:\n- Currency pair selection and depth\n- Forex-specific trading conditions\n- Understanding of forex market dynamics\n- Support for forex-specific strategies\n\n### Business Model\n\nForex Funded Trader operates the standard evaluation-based prop firm model with a forex focus:\n\n1. **Challenge Revenue:** Fees for forex-focused evaluations\n2. **Simulated Forex Trading:** Demo accounts with forex emphasis\n3. **Profit Sharing:** Split of simulated forex profits\n4. **Specialized Services:** Forex-focused tools and support\n\nThe forex specialization provides:\n- Focused instrument selection\n- Deep expertise in currency markets\n- Forex-specific educational content\n- Community of forex-focused traders\n\n### Key Milestones\n\n| Year | Milestone |\n|------|-----------|\n| 2022-2023 | Company founded with forex focus |\n| 2023 | Platform development for forex trading |\n| 2024 | Official launch with forex challenge programs |\n| 2024-2025 | Initial trader payouts and growth |\n| 2025-2026 | Market expansion and reputation building |\n\n### Company Structure\n\n- **Legal Entity:** Registered business (details on official website)\n- **Business Type:** Forex-focused evaluation prop trading\n- **Ownership:** Privately held\n- **Team:** Forex traders, technologists, support staff\n- **Operations:** Online-first, forex-specialist focus\n\n### Mission & Vision\n\n**Mission:** To provide forex traders with the most focused, fair, and reliable funded trading experience in the industry.\n\n**Vision:** To become the premier prop firm for forex traders worldwide, known for excellent trading conditions and genuine support for currency traders.\n\n**Core Values:**\n- Forex expertise and focus\n- Fair treatment of all traders\n- Transparent operations\n- Reliable and fast payouts\n- Community-driven development\n\n### Unique Value Proposition\n\nWhat differentiates Forex Funded Trader:\n1. **Forex Specialization:** Deep expertise in currency markets\n2. **Tailored Experience:** Platform and support for forex traders\n3. **Instrument Depth:** Comprehensive forex pair selection\n4. **Community:** Forex-focused trading community\n5. **Education:** Forex-specific educational content\n\n### Target Audience\n\nForex Funded Trader specifically serves:\n- Retail forex traders (primary audience)\n- Day traders focused on currencies\n- Swing traders on forex pairs\n- EA traders on forex platforms\n- Forex-focused algorithmic traders\n- International traders seeking forex capital\n\n---\n\n## 2. REGULATION & LICENSING\n\n### Regulatory Framework\n\nForex Funded Trader operates within the standard prop firm regulatory position:\n\n**Regulatory Status:**\n- Not regulated as financial services firm\n- Operates as forex training/evaluation company\n- Simulated forex trading environment\n- Standard industry regulatory position\n\n### Why Standard Financial Regulation Doesn't Apply\n\n**Simulated Environment:**\n- All forex trading in demo accounts\n- No real capital at risk\n- No client fund deposits\n- No actual forex broker services\n\n**Educational Classification:**\n- Forex evaluation as training service\n- Challenge fees for evaluation access\n- No forex brokerage or investment services\n\n### Compliance Measures\n\n**KYC Procedures:**\n- Identity verification for funded accounts\n- Document verification\n- Age verification (18+)\n\n**AML Compliance:**\n- Transaction monitoring\n- Payout verification\n- Sanctions screening\n\n**Data Protection:**\n- Privacy policy\n- GDPR compliance for EU\n- Secure data handling\n\n### Forex-Specific Considerations\n\n**Traders Should Note:**\n- No forex broker regulation applies\n- Simulated forex execution, not real\n- Terms of service govern relationship\n- Jurisdiction as specified in terms\n\n---\n\n## 3. CHALLENGE RULES & PHASES ⭐ MOST IMPORTANT\n\n### Forex-Focused Challenge Structure\n\nForex Funded Trader offers challenges specifically designed for forex traders:\n\n### 2-STEP CHALLENGE\n\n#### Phase 1: Forex Evaluation\n\n| Rule | Detail |\n|------|--------|\n| **Profit Target** | 8-10% |\n| **Maximum Daily Loss** | 5% |\n| **Maximum Total Loss** | 8-10% |\n| **Minimum Trading Days** | 3-5 |\n| **Time Limit** | 30-60 days |\n| **Weekend Holding** | Allowed |\n| **News Trading** | Permitted |\n| **Instruments** | Forex pairs (primary) |\n\n#### Phase 2: Verification\n\n| Rule | Detail |\n|------|--------|\n| **Profit Target** | 5% |\n| **Maximum Daily Loss** | 5% |\n| **Maximum Total Loss** | 8-10% |\n| **Minimum Trading Days** | 3-5 |\n| **Time Limit** | 60-90 days |\n\n### 1-STEP CHALLENGE\n\n| Rule | Detail |\n|------|--------|\n| **Profit Target** | 10-12% |\n| **Maximum Daily Loss** | 5% |\n| **Maximum Total Loss** | 10% |\n| **Minimum Trading Days** | 5-7 |\n| **Time Limit** | 30-45 days |\n\n### FUNDED ACCOUNT\n\n| Rule | Detail |\n|------|--------|\n| **Profit Target** | None |\n| **Maximum Daily Loss** | 5% |\n| **Maximum Total Loss** | 8-10% |\n| **Profit Split** | 80% standard |\n| **Payout Frequency** | Bi-weekly |\n\n### Forex-Specific Trading Rules\n\n**Currency Pairs:**\n- Major pairs: Full access\n- Minor pairs: Full access\n- Exotic pairs: May have restrictions (check terms)\n- Leverage: Up to 1:50 (typical)\n\n**Position Management:**\n- No lot size restrictions (forex standard)\n- Multiple pairs allowed\n- Hedging permitted (check terms)\n- Correlation rules may apply\n\n**Session Flexibility:**\n- All forex sessions available\n- Asian, European, US sessions\n- Weekend holding permitted\n- No session restrictions\n\n---\n\n## 4. ACCOUNT TYPES & PRICING\n\n### Account Sizes (Forex-Focused)\n\n| Size | Approx. Fee (2-Step) | Target Trader |\n|------|---------------------|---------------|\n| $5,000 | $30-50 | Practice |\n| $10,000 | $50-80 | Beginners |\n| $25,000 | $100-150 | Developing |\n| $50,000 | $180-260 | Intermediate |\n| $100,000 | $300-450 | Serious |\n| $200,000 | $550-800 | Professional |\n\n### Forex Pair Selection\n\n**Typically Available:**\n- EUR/USD, GBP/USD, USD/JPY, USD/CHF\n- AUD/USD, USD/CAD, NZD/USD\n- EUR/GBP, EUR/JPY, GBP/JPY\n- AUD/JPY, EUR/AUD, and more\n- 30-50+ forex pairs\n\n**May Have Restrictions:**\n- Some exotic pairs\n- Very illiquid pairs\n- Specific exotic crosses\n\n### Fee Refund Policy\n- 100% refund with first payout\n- Standard industry feature\n- Automatic processing\n\n### Payment Methods\n- Credit/Debit cards\n- PayPal\n- Cryptocurrency\n- Bank transfer\n\n### Free Trial\n- Forex demo challenge\n- Limited duration\n- Fixed parameters\n- Practice without risk\n\n---\n\n## 5. TRADING CONDITIONS\n\n### Trading Platforms (Forex Optimized)\n\n#### MetaTrader 4 (MT4)\n- Industry standard for forex\n- Full EA support\n- 30+ indicators\n- Mobile and web\n- Optimized for forex\n\n#### MetaTrader 5 (MT5)\n- Advanced MT4 successor\n- More timeframes (21)\n- Depth of market\n- Economic calendar\n- Enhanced for forex\n\n#### cTrader (if available)\n- Modern forex platform\n- Advanced charting\n- cTrader Copy for forex\n- C# API for forex EAs\n\n### Forex Instruments Available\n\n**Major Pairs (Highest Priority):**\n- EUR/USD: Tightest spreads\n- GBP/USD: Good volatility\n- USD/JPY: High liquidity\n- USD/CHF: Safe haven dynamics\n- AUD/USD: Commodity currency\n- USD/CAD: Oil-linked\n- NZD/USD: Risk sentiment\n\n**Minor Pairs:**\n- EUR/GBP, EUR/JPY, GBP/JPY\n- AUD/NZD, AUD/JPY, NZD/JPY\n- EUR/AUD, EUR/CAD, GBP/CAD\n- 20-30+ minor pairs\n\n**Exotic Pairs (Check Availability):**\n- USD/TRY, USD/ZAR, USD/MXN\n- EUR/TRY, USD/SEK, USD/NOK\n- Varies by firm\n\n### Forex Leverage\n\n| Pair Type | Maximum Leverage |\n|-----------|-----------------|\n| Major Pairs | 1:50 |\n| Minor Pairs | 1:30-50 |\n| Exotic Pairs | 1:20-30 |\n\n### Spreads & Execution\n\n**Spread Types:**\n- Standard: Wider spreads, no commission\n- Raw: Tight spreads + commission\n- Typical EUR/USD: 0.1-1.0 pips (raw), 1.0-1.5 (standard)\n\n**Execution:**\n- Simulated but realistic\n- Market execution model\n- Fast order processing\n- Low latency targets\n\n---\n\n## 6. PAYOUTS & PROFIT SPLIT\n\n### Forex Profit Split\n\n| Level | Split |\n|-------|-------|\n| Standard | 80% |\n| Scaled | 85-90% |\n| Premium | Up to 90% |\n\n### Payout Schedule\n- Bi-weekly (every 14 days)\n- Processing: 24-72 hours\n- Multiple payment methods\n- Forex-friendly options\n\n### Payout Requirements\n1. Challenge passed\n2. KYC complete\n3. Trading days met\n4. Payout request submitted\n\n### Fee Refund with Payout\n- 100% challenge fee refund\n- Included with first payout\n- Automatic processing\n- Industry standard\n\n---\n\n## 7. SCALING PLAN\n\n### Forex Scaling Requirements\n1. 2+ months active funded\n2. 10%+ profit achieved\n3. 2+ payouts received\n4. No rule violations\n\n### Scaling Benefits\n- 25% account increase\n- Higher profit split\n- Forex-focused support\n- Priority features\n\n### Scaling Example\n\n$100,000 starting forex account:\n- Month 3: $125,000\n- Month 6: $150,000\n- Month 9: $175,000\n- Month 12: $200,000\n\n---\n\n## 8. USER REVIEWS\n\n### Expected Forex-Trader Feedback\n\n**Positive Themes:**\n- Forex-focused experience\n- Good pair selection\n- Fair forex rules\n- Reliable payouts\n\n**Negative Themes:**\n- Newer firm, limited history\n- Standard rules (not unique)\n- Building reputation\n- Community still growing\n\n### Review Sources\n- Trustpilot reviews\n- Forex forums\n- Reddit discussions\n- YouTube videos\n- Discord communities\n\n---\n\n## 9. COMPETITIVE POSITION\n\n### Forex Prop Firm Comparison\n\n| Factor | Forex Funded Trader | FTMO | FundedNext | Forex-specific firms |\n|--------|---------------------|------|------------|---------------------|\n| Focus | Forex-specialist | General | General | Forex |\n| Forex Pairs | 30-50+ | 40+ | 40+ | Varies |\n| Platform | MT4/MT5 focus | Multi-platform | Multi-platform | MT4/MT5 |\n| Brand | Newer | Leader | Strong | Various |\n| Pricing | Competitive | Premium | Mid-range | Varies |\n\n### Forex-Specific Advantages\n- Focused forex expertise\n- Tailored experience\n- Forex community\n- Specialized support\n\n### Forex-Specific Disadvantages\n- Less asset diversity\n- Newer, unproven\n- Smaller scale\n- Limited history\n\n---\n\n## 10. AFFILIATE PROGRAM\n\n### Forex Affiliate Structure\n- CPA: $25-75 per forex trader referral\n- Revenue share: 10-15%\n- Forex-focused marketing materials\n- Forex community targeting\n\n### Requirements\n- Application and approval\n- Forex content compliance\n- FTC disclosure\n- No misleading claims\n\n---\n\n## 11. PAYOUT TRACK RECORD\n\n### Building Forex Credibility\n- Document forex payouts\n- Forex trader testimonials\n- Social media proofs\n- Community verification\n\n### Verification Methods\n- Trustpilot reviews\n- Forex forum discussions\n- YouTube payout videos\n- Social media proofs\n\n---\n\n## 12. RULES TRANSPARENCY\n\n### Forex Rule Documentation\n- Clear forex pair rules\n- Leverage specifications\n- Spread information\n- Position size rules\n\n### Forex-Specific Ambiguities to Watch\n- Exotic pair restrictions\n- Correlation rules\n- Session-specific rules\n- News trading nuances\n\n---\n\n## 13. PARTNERSHIPS\n\n### Forex Technology Partners\n- MetaQuotes (MT4/MT5)\n- Liquidity providers\n- Payment processors\n- KYC providers\n\n### Forex Community Partners\n- Forex education providers\n- Forex signal services\n- Forex communities\n- Content creators\n\n---\n\n## 14. CHARITY & CSR\n\n### Forex Community Impact\n- Forex education access\n- Trader development\n- Community support\n- Financial inclusion\n\n### Potential Initiatives\n- Free forex education\n- Charity trading events\n- Community programs\n- Educational scholarships\n\n---\n\n## 15. AWARDS & RECOGNITION\n\n### Forex Industry Awards\n- Best Forex Prop Firm\n- Best Forex Challenge\n- Forex Innovation Award\n- Rising Forex Star\n\n### Building Forex Reputation\n- Forex community engagement\n- Industry recognition\n- Media coverage\n- Peer acknowledgment\n\n---\n\n## 16. PROMOTIONS & OFFERS\n\n### Forex-Focused Promotions\n- Forex challenge discounts\n- Forex pair bonuses\n- Seasonal forex sales\n- First-time trader offers\n\n### Loyalty Programs\n- Returning forex trader discounts\n- Forex VIP tiers\n- Referral bonuses\n- Forex loyalty points\n\n---\n\n## SUMMARY & RATING\n\n### Forex Funded Trader Assessment\n\nForex Funded Trader offers a specialized approach for forex-focused traders, providing a platform designed specifically for currency trading. This specialization can be advantageous for traders who primarily trade forex and prefer a focused experience over multi-asset platforms.\n\n### Strengths\n✅ Forex-specialized focus\n✅ Tailored experience for forex traders\n✅ Modern MT4/MT5 platforms\n✅ Competitive conditions\n✅ Forex community development\n\n### Weaknesses\n❌ Limited track record\n❌ Less asset diversity\n❌ Building reputation\n❌ Unproven long-term\n❌ Standard rules\n\n### Rating\n\n| Category | Score |\n|----------|-------|\n| Challenge Rules | 7/10 |\n| Payouts & Reliability | 6.5/10 |\n| Trading Conditions (Forex) | 7.5/10 |\n| Scaling & Growth | 6.5/10 |\n| User Reviews | 6/10 |\n| Transparency | 7/10 |\n| **OVERALL** | **6.8/10** |\n\n### Forex Trader Recommendation\n\n**Best For:**\n- Pure forex traders\n- MT4/MT5 users\n- Forex EA traders\n- Those wanting focused experience\n- Forex community seekers\n\n**Considerations:**\n- Limited to forex (primarily)\n- Newer firm, verify operations\n- Check forex pair availability\n- Compare with generalist firms\n\n**Risk Level:** Moderate (typical for newer firms)\n\n---\n\n*Report compiled April 2026. Verify with official sources.*\n\n*Last Updated: April 2, 2026*\n\n---\n\n## APPENDIX A: FOREX TRADING ESSENTIALS\n\n### Currency Pair Basics\n\n**What is a Currency Pair?**\nA currency pair consists of two currencies:\n- **Base Currency:** The first currency (e.g., EUR in EUR/USD)\n- **Quote Currency:** The second currency (e.g., USD in EUR/USD)\n- **Exchange Rate:** How much of quote currency equals one unit of base\n\n**Example:**\nEUR/USD = 1.1000 means:\n- 1 EUR = 1.10 USD\n- To buy 1 EUR, you pay 1.10 USD\n- To sell 1 EUR, you receive 1.10 USD\n\n### Pip Value Calculations\n\n**What is a Pip?**\n- Standard pip: 0.0001 (for most pairs)\n- JPY pairs: 0.01\n- Pipette: 0.00001 (fractional pip)\n\n**Pip Value Formula:**\n```\nPip Value = (Pip Size × Trade Size) / Exchange Rate\n```\n\n**Examples:**\n\n| Pair | Lot Size | Pip Value (approx) |\n|------|----------|-------------------|\n| EUR/USD | 1 Standard | $10 per pip |\n| EUR/USD | 1 Mini | $1 per pip |\n| GBP/USD | 1 Standard | $10 per pip |\n| USD/JPY | 1 Standard | ~$9 per pip (varies) |\n\n### Position Sizing for Forex\n\n**Risk-Based Sizing:**\n```\nPosition Size (lots) = Account × Risk% / (Pips × Pip Value)\n```\n\n**Example for $100,000 Account:**\n- Risk per trade: 1% = $1,000\n- Stop loss: 50 pips\n- EUR/USD pip value: $10\n- Position size: $1,000 / (50 × $10) = 2.0 standard lots\n\n### Forex Session Times\n\n| Session | Hours (UTC) | Best Pairs | Characteristics |\n|---------|-------------|------------|-----------------|\n| Sydney | 22:00-07:00 | AUD, NZD | Low volatility |\n| Tokyo | 00:00-09:00 | JPY, AUD | Medium volatility |\n| London | 08:00-17:00 | EUR, GBP | High volatility |\n| New York | 13:00-22:00 | USD, CAD | High volatility |\n| Overlap (Lon-NY) | 13:00-17:00 | All majors | Highest volatility |\n\n---\n\n## APPENDIX B: FOREX FUNDAMENTAL ANALYSIS\n\n### Key Economic Indicators for Forex\n\n**Interest Rate Decisions:**\n- Most important forex driver\n- Higher rates = stronger currency (generally)\n- Central bank meetings critical\n- Forward guidance matters\n\n**Non-Farm Payrolls (NFP):**\n- US employment report\n- Released first Friday of month\n- Major USD volatility event\n- Watch actual vs. forecast\n\n**GDP (Gross Domestic Product):**\n- Economic growth measure\n- Higher GDP = stronger currency\n- Quarterly release\n- Market moves on surprises\n\n**Inflation (CPI/PPI):**\n- Price level changes\n- Higher inflation may lead to rate hikes\n- Purchasing power impact\n- Key central bank input\n\n**PMI (Purchasing Managers Index):**\n- Manufacturing/services health\n- Above 50 = expansion\n- Below 50 = contraction\n- Leading indicator\n\n### Central Bank Impact\n\n**Federal Reserve (USD):**\n- FOMC meetings (8 times/year)\n- Interest rate decisions\n- Quantitative easing/tightening\n- Forward guidance\n\n**European Central Bank (EUR):**\n- Monthly meetings\n- Interest rate policy\n- Asset purchase programs\n- Economic projections\n\n**Bank of England (GBP):**\n- Monthly meetings\n- Inflation targeting\n- Brexit impacts\n- Economic forecasts\n\n**Bank of Japan (JPY):**\n- Yield curve control\n- Ultra-loose policy\n- Intervention risk\n- Kuroda/BoJ statements\n\n### Forex Calendar Strategy\n\n**Pre-Event:**\n- Reduce position sizes\n- Widen stops\n- Close vulnerable positions\n- Set alerts\n\n**During Event:**\n- No new positions\n- Wait for volatility\n- Watch actual vs. forecast\n- Note market reaction\n\n**Post-Event:**\n- Wait 15-30 minutes\n- Look for trend confirmation\n- Trade the reaction\n- Use wider stops initially\n\n---\n\n## APPENDIX C: FOREX TECHNICAL ANALYSIS\n\n### Essential Forex Chart Patterns\n\n**Trend Patterns:**\n- Head and Shoulders (reversal)\n- Double Top/Bottom (reversal)\n- Ascending/Descending Triangles\n- Pennants and Flags (continuation)\n- Wedges (reversal)\n\n**Candlestick Patterns for Forex:**\n\n**Reversal Patterns:**\n- Doji (indecision)\n- Hammer/Hanging Man\n- Engulfing (bullish/bearish)\n- Morning/Evening Star\n- Piercing Line/Dark Cloud\n\n**Continuation Patterns:**\n- Rising/Falling Three Methods\n- Mat Hold\n- Tasuki Gap\n- Side-by-Side White Lines\n\n### Key Forex Levels\n\n**Psychological Levels:**\n- Round numbers (1.1000, 1.2000, etc.)\n- Half levels (1.1050, 1.1150)\n- Quarter levels (1.1025, 1.1075)\n- Big figure levels\n\n**Technical Levels:**\n- Swing highs and lows\n- Fibonacci retracements\n- Moving averages\n- Pivot points\n\n### Forex-Specific Indicators\n\n**Best for Forex:**\n- Moving Averages (20, 50, 200)\n- RSI (14 period)\n- MACD (12, 26, 9)\n- Bollinger Bands (20, 2)\n- Stochastic (14, 3, 3)\n\n**Forex Session Indicators:**\n- Session highlight indicators\n- Overlap period markers\n- Volatility indicators\n\n---\n\n## APPENDIX D: FOREX STRATEGY LIBRARY\n\n### Strategy 1: London Breakout\n\n**Concept:** Trade breakouts from Asian session range during London open\n\n**Setup:**\n1. Mark Asian session high/low (Tokyo range)\n2. Wait for London open (8:00 UTC)\n3. Enter on breakout of Asian range\n4. Stop opposite side of range\n5. Target 1:2 or 1:3 R:R\n\n**Best Pairs:** EUR/USD, GBP/USD, EUR/JPY\n**Time:** London open\n**Success Rate:** 45-55%\n\n### Strategy 2: Trend Following with MA\n\n**Concept:** Trade in trend direction using moving average crossovers\n\n**Setup:**\n1. Identify trend on 4H/Daily\n2. Wait for pullback to MA\n3. Enter on bullish/bearish candle\n4. Stop below/above swing\n5. Target previous high/low\n\n**Best Pairs:** All major pairs\n**Timeframes:** 4H, Daily\n**Success Rate:** 40-50%\n\n### Strategy 3: Support/Resistance Bounce\n\n**Concept:** Buy support, sell resistance in ranging markets\n\n**Setup:**\n1. Identify clear S/R levels\n2. Wait for price to reach level\n3. Enter on reversal candle\n4. Stop beyond S/R level\n5. Target opposite level\n\n**Best Pairs:** All pairs in range\n**Timeframes:** 1H, 4H\n**Success Rate:** 55-65%\n\n### Strategy 4: News Fade\n\n**Concept:** Fade extreme news reactions at key levels\n\n**Setup:**\n1. Identify key levels before news\n2. Wait for news release\n3. If price reaches key level on spike, fade\n4. Stop beyond the spike\n5. Target return to pre-news level\n\n**Best Pairs:** Major pairs (EUR/USD, GBP/USD)\n**Time:** News events\n**Success Rate:** 40-50% (higher R:R)\n\n---\n\n## APPENDIX E: FOREX RISK MANAGEMENT\n\n### Forex-Specific Risk Factors\n\n**Spread Risk:**\n- Spreads widen during news\n- Spreads widen at session edges\n- Exotic pairs have wider spreads\n- Account for spread in calculations\n\n**Slippage Risk:**\n- News events cause slippage\n- Fast markets increase slippage\n- Larger positions = more slippage\n- Limit news trading size\n\n**Gap Risk:**\n- Weekend gaps common\n- Gaps can be significant\n- Stops may not fill at target\n- Reduce weekend exposure\n\n**Correlation Risk:**\n- EUR/USD and GBP/USD often correlated\n- AUD/USD and NZD/USD correlated\n- USD pairs move together\n- Don't overexpose to USD\n\n### Position Sizing Rules\n\n**Conservative (Challenge Recommended):**\n- Risk 0.5-0.75% per trade\n- Maximum 3-4 concurrent positions\n- Total risk: 2-3% at any time\n- Daily loss limit: 2-3%\n\n**Moderate:**\n- Risk 1% per trade\n- Maximum 5 concurrent positions\n- Total risk: 3-5% at any time\n- Daily loss limit: 3-4%\n\n**Aggressive (Not Recommended for Challenges):**\n- Risk 1.5-2% per trade\n- Unlimited positions\n- Total risk: 5%+\n- Daily loss limit: 5%\n\n### Drawdown Management\n\n**If Drawdown Reaches 3%:**\n- Reduce position sizes by 50%\n- Review recent trades\n- Consider taking a break\n- Reassess market conditions\n\n**If Drawdown Reaches 5%:**\n- Stop trading temporarily\n- Complete trade review\n- Adjust strategy if needed\n- Resume only when confident\n\n---\n\n## APPENDIX F: FOREX PLATFORM OPTIMIZATION\n\n### MT4/MT5 Setup for Forex\n\n**Essential Configuration:**\n1. Multiple timeframes loaded\n2. Templates saved for each strategy\n3. Indicators properly configured\n4. Alert system set up\n5. Expert advisors (if using)\n\n**Recommended Templates:**\n- Trend template (MAs, MACD, ADX)\n- Range template (RSI, Stochastic, Bollinger)\n- Scalping template (1-5M charts, tight indicators)\n- Swing template (4H-Daily, wider parameters)\n\n### Forex-Specific Indicators\n\n**Session Indicators:**\n- Show trading sessions on chart\n- Highlight overlaps\n- Mark key times\n\n**Spread Indicators:**\n- Display current spread\n- Track spread history\n- Alert on widening\n\n**Pivot Point Indicators:**\n- Automatic pivot calculation\n- Daily/weekly/monthly pivots\n- Support/resistance levels\n\n### VPS for Forex EAs\n\n**Requirements:**\n- Low latency to broker servers\n- 24/5 uptime minimum\n- Adequate RAM and CPU\n- Reliable provider\n\n**Recommended VPS Specs:**\n- 2+ GHz CPU\n- 2+ GB RAM\n- 40+ GB storage\n- Windows Server OS\n\n---\n\n## APPENDIX G: FOREX JOURNAL TEMPLATE\n\n### Daily Forex Journal\n\n**Pre-Trade Entry:**\n```\nDate: ___________\nPair: ___________\nDirection: Long / Short\nEntry: ___________\nStop Loss: ___________\nTake Profit: ___________\nLots: ___________\nRisk ($): ___________\nRisk (%): ___________%\nSession: Tokyo / London / NY\nReason: ___________\n```\n\n**Post-Trade Entry:**\n```\nExit: ___________\nResult: Win / Loss / BE\nP/L ($): ___________\nP/L (pips): ___________\nDuration: ___________\nR-Multiple: ___________\nSpread at Entry: ___________\nSpread at Exit: ___________\nNews Impact: Yes / No\nLessons: ___________\n```\n\n### Weekly Forex Review\n\n```\nWeek of: ___________\n\nPairs Traded: ___________\nBest Pair: ___________\nWorst Pair: ___________\n\nSession Performance:\n- Tokyo: ___________\n- London: ___________\n- New York: ___________\n\nTotal Trades: ___________\nWin Rate: ___________%\nProfit Factor: ___________\nBest Trade: ___________\nWorst Trade: ___________\n\nChallenge Progress:\n- Balance: $___________\n- Target: $___________\n- Progress: ___________% \n- Daily Loss Remaining: ___________\n- Total Loss Remaining: ___________\n```\n\n---\n\n*This comprehensive report on Forex Funded Trader provides detailed information for forex traders evaluating this prop firm. All specific details should be verified directly with the firm's official website.*\n\n*Report compiled as of April 2026.*\n\n---\n\n## APPENDIX H: FOREX PAIR DEEP DIVE\n\n### EUR/USD Analysis\n\n**Characteristics:**\n- Most traded pair globally\n- Tightest spreads\n- High liquidity\n- Good trending and ranging behavior\n\n**Best Trading Times:**\n- London session (highest volume)\n- NY-London overlap (peak activity)\n- Avoid early Asian session (low volume)\n\n**Key Drivers:**\n- ECB vs Fed policy\n- Eurozone vs US economic data\n- Risk sentiment\n- USD safe-haven flows\n\n**Challenge Rating:** ★★★★★ (Excellent for challenges)\n\n### GBP/USD Analysis\n\n**Characteristics:**\n- Second most popular pair\n- Higher volatility than EUR/USD\n- Good trending potential\n- Wider spreads than EUR/USD\n\n**Best Trading Times:**\n- London session\n- London-NY overlap\n- UK economic data releases\n\n**Key Drivers:**\n- BOE vs Fed policy\n- UK economic data\n- Brexit-related news\n- Risk sentiment\n\n**Challenge Rating:** ★★★★★ (Good volatility for targets)\n\n### USD/JPY Analysis\n\n**Characteristics:**\n- Third most traded pair\n- Lower volatility than GBP pairs\n- Strong trends\n- Intervention risk\n\n**Best Trading Times:**\n- Tokyo session\n- London session\n- US session\n\n**Key Drivers:**\n- BOJ vs Fed policy\n- Japanese economic data\n- Risk sentiment (JPY safe haven)\n- Intervention threats\n\n**Challenge Rating:** ★★★★☆ (Good for steady gains)\n\n### XAU/USD (Gold) Analysis\n\n**Characteristics:**\n- High volatility\n- Strong trends\n- Safe haven status\n- Wider spreads\n\n**Best Trading Times:**\n- London session\n- NY session\n- During risk events\n\n**Key Drivers:**\n- Real interest rates\n- USD strength\n- Inflation expectations\n- Geopolitical events\n- Central bank buying\n\n**Challenge Rating:** ★★★★★ (High profit potential)\n\n---\n\n## APPENDIX I: FOREX CORRELATION GUIDE\n\n### Major Pair Correlations\n\n**Positive Correlations:**\n- EUR/USD and GBP/USD (often move together)\n- AUD/USD and NZD/USD (commodity currencies)\n- USD/CHF and USD/JPY (safe havens)\n\n**Negative Correlations:**\n- EUR/USD and USD/CHF (opposite movements)\n- EUR/USD and USD/JPY (risk-on vs safe haven)\n- GBP/USD and USD/JPY (complex relationship)\n\n### Correlation Risk in Challenges\n\n**Problem:** Trading highly correlated pairs doubles your risk\n\n**Solution:**\n1. Identify correlated positions\n2. Reduce size on correlated trades\n3. Consider correlation in total risk\n4. Use correlation as confirmation, not additional position\n\n**Example:**\n- Long EUR/USD at 1% risk\n- Long GBP/USD at 1% risk\n- If correlated, you're effectively risking 2% on USD weakness\n- Reduce to 0.5% each or only take one\n\n---\n\n## APPENDIX J: FOREX TAX CONSIDERATIONS\n\n### Tax Treatment of Forex Profits\n\n**Important:** Tax treatment varies significantly by jurisdiction. Consult a tax professional.\n\n**US Traders:**\n- Section 988: Ordinary income treatment\n- Section 1256: 60/40 capital gains treatment\n- May elect which applies\n- Consult tax advisor\n\n**UK Traders:**\n- Spread betting: Tax-free (no CGT or stamp duty)\n- CFD trading: Capital gains tax applies\n- Consult UK tax advisor\n\n**EU Traders:**\n- Varies by country\n- Income tax or capital gains\n- Some exemptions possible\n- Consult local advisor\n\n**Australian Traders:**\n- CGT may apply\n- Business income treatment possible\n- Consult Australian tax advisor\n\n### Record Keeping for Forex\n\n**Maintain Records Of:**\n- All trade records\n- Account statements\n- P/L calculations\n- Fee payments\n- Payout receipts\n- Communication with firm\n\n---\n\n*Final appendix of this comprehensive Forex Funded Trader report. All information should be verified with official sources.*\n\n*Report complete as of April 2026.*\n",
  "_provenance": {
    "sources": [
      {
        "path": "C:\\OpenclawAISE\\Forex Brokers\\forexbrokeratings\\data\\prop-firms\\forex-funded-trader.json",
        "bytes": 29085
      }
    ],
    "mergedAt": "2026-04-15T12:42:26.687Z",
    "mergeOpCount": 0
  },
  "_mergeLog": []
}