{
  "jurisdictions": [
    {
      "id": "gb-fca",
      "name": "United Kingdom",
      "city": "London",
      "country": "United Kingdom",
      "countryCode": "GB",
      "lat": 51.5074,
      "lng": -0.1278,
      "regulator": "FCA",
      "brokerCount": 98,
      "avgRebatePerLot": 6.1,
      "trustScore": 9.4,
      "color": "#4ADE80"
    },
    {
      "id": "au-asic",
      "name": "Australia",
      "city": "Sydney",
      "country": "Australia",
      "countryCode": "AU",
      "lat": -33.8688,
      "lng": 151.2093,
      "regulator": "ASIC",
      "brokerCount": 69,
      "avgRebatePerLot": 6.1,
      "trustScore": 9.4,
      "color": "#4ADE80"
    },
    {
      "id": "cy-cysec",
      "name": "Cyprus",
      "city": "Limassol",
      "country": "Cyprus",
      "countryCode": "CY",
      "lat": 34.7071,
      "lng": 33.0226,
      "regulator": "CySEC",
      "brokerCount": 97,
      "avgRebatePerLot": 6.1,
      "trustScore": 9.4,
      "color": "#22D3EE"
    },
    {
      "id": "us-nfa",
      "name": "United States",
      "city": "Chicago",
      "country": "United States",
      "countryCode": "US",
      "lat": 41.8781,
      "lng": -87.6298,
      "regulator": "NFA",
      "brokerCount": 46,
      "avgRebatePerLot": 6.1,
      "trustScore": 9.4,
      "color": "#4ADE80"
    },
    {
      "id": "ch-finma",
      "name": "Switzerland",
      "city": "Zurich",
      "country": "Switzerland",
      "countryCode": "CH",
      "lat": 47.3769,
      "lng": 8.5417,
      "regulator": "FINMA",
      "brokerCount": 7,
      "avgRebatePerLot": 6.1,
      "trustScore": 9.4,
      "color": "#4ADE80"
    },
    {
      "id": "de-bafin",
      "name": "Germany",
      "city": "Frankfurt",
      "country": "Germany",
      "countryCode": "DE",
      "lat": 50.1109,
      "lng": 8.6821,
      "regulator": "BaFin",
      "brokerCount": 15,
      "avgRebatePerLot": 6.1,
      "trustScore": 9.4,
      "color": "#4ADE80"
    },
    {
      "id": "sg-mas",
      "name": "Singapore",
      "city": "Singapore",
      "country": "Singapore",
      "countryCode": "SG",
      "lat": 1.3521,
      "lng": 103.8198,
      "regulator": "MAS",
      "brokerCount": 15,
      "avgRebatePerLot": 6.1,
      "trustScore": 9.4,
      "color": "#4ADE80"
    },
    {
      "id": "jp-fsa",
      "name": "Japan",
      "city": "Tokyo",
      "country": "Japan",
      "countryCode": "JP",
      "lat": 35.6762,
      "lng": 139.6503,
      "regulator": "JFSA",
      "brokerCount": 23,
      "avgRebatePerLot": 6.1,
      "trustScore": 9.4,
      "color": "#4ADE80"
    },
    {
      "id": "hk-sfc",
      "name": "Hong Kong",
      "city": "Hong Kong",
      "country": "Hong Kong",
      "countryCode": "HK",
      "lat": 22.3193,
      "lng": 114.1694,
      "regulator": "SFC",
      "brokerCount": 7,
      "avgRebatePerLot": 6.1,
      "trustScore": 9.4,
      "color": "#22D3EE"
    },
    {
      "id": "ae-dfsa",
      "name": "UAE (Dubai)",
      "city": "Dubai",
      "country": "United Arab Emirates",
      "countryCode": "AE",
      "lat": 25.2048,
      "lng": 55.2708,
      "regulator": "DFSA",
      "brokerCount": 54,
      "avgRebatePerLot": 7,
      "trustScore": 8.2,
      "color": "#22D3EE"
    },
    {
      "id": "za-fsca",
      "name": "South Africa",
      "city": "Johannesburg",
      "country": "South Africa",
      "countryCode": "ZA",
      "lat": -26.2041,
      "lng": 28.0473,
      "regulator": "FSCA",
      "brokerCount": 0,
      "avgRebatePerLot": 7,
      "trustScore": 8.2,
      "color": "#22D3EE"
    },
    {
      "id": "ca-ciro",
      "name": "Canada",
      "city": "Toronto",
      "country": "Canada",
      "countryCode": "CA",
      "lat": 43.6532,
      "lng": -79.3832,
      "regulator": "CIRO",
      "brokerCount": 9,
      "avgRebatePerLot": 6.1,
      "trustScore": 9.4,
      "color": "#4ADE80"
    },
    {
      "id": "nz-fma",
      "name": "New Zealand",
      "city": "Auckland",
      "country": "New Zealand",
      "countryCode": "NZ",
      "lat": -36.8485,
      "lng": 174.7633,
      "regulator": "FMA",
      "brokerCount": 8,
      "avgRebatePerLot": 6.1,
      "trustScore": 9.4,
      "color": "#4ADE80"
    },
    {
      "id": "mt-mfsa",
      "name": "Malta",
      "city": "Valletta",
      "country": "Malta",
      "countryCode": "MT",
      "lat": 35.8989,
      "lng": 14.5146,
      "regulator": "MFSA",
      "brokerCount": 7,
      "avgRebatePerLot": 6.1,
      "trustScore": 9.4,
      "color": "#22D3EE"
    },
    {
      "id": "ie-cbi",
      "name": "Ireland",
      "city": "Dublin",
      "country": "Ireland",
      "countryCode": "IE",
      "lat": 53.3498,
      "lng": -6.2603,
      "regulator": "CBI",
      "brokerCount": 2,
      "avgRebatePerLot": 6.1,
      "trustScore": 9.4,
      "color": "#4ADE80"
    },
    {
      "id": "lu-cssf",
      "name": "Luxembourg",
      "city": "Luxembourg",
      "country": "Luxembourg",
      "countryCode": "LU",
      "lat": 49.6116,
      "lng": 6.1319,
      "regulator": "CSSF",
      "brokerCount": 1,
      "avgRebatePerLot": 6.1,
      "trustScore": 9.4,
      "color": "#4ADE80"
    },
    {
      "id": "bs-scb",
      "name": "Bahamas",
      "city": "Nassau",
      "country": "Bahamas",
      "countryCode": "BS",
      "lat": 25.0343,
      "lng": -77.3963,
      "regulator": "SCB",
      "brokerCount": 13,
      "avgRebatePerLot": 8,
      "trustScore": 7,
      "color": "#A78BFA"
    },
    {
      "id": "vg-fsc",
      "name": "BVI",
      "city": "Road Town",
      "country": "British Virgin Islands",
      "countryCode": "VG",
      "lat": 18.4207,
      "lng": -64.64,
      "regulator": "BVI FSC",
      "brokerCount": 2,
      "avgRebatePerLot": 8,
      "trustScore": 7,
      "color": "#A78BFA"
    },
    {
      "id": "sc-fsa",
      "name": "Seychelles",
      "city": "Victoria",
      "country": "Seychelles",
      "countryCode": "SC",
      "lat": -4.6191,
      "lng": 55.4513,
      "regulator": "FSA Seychelles",
      "brokerCount": 91,
      "avgRebatePerLot": 8,
      "trustScore": 7,
      "color": "#A78BFA"
    },
    {
      "id": "vc-svg",
      "name": "St. Vincent",
      "city": "Kingstown",
      "country": "St. Vincent & the Grenadines",
      "countryCode": "VC",
      "lat": 13.16,
      "lng": -61.2248,
      "regulator": "SVG FSA",
      "brokerCount": 0,
      "avgRebatePerLot": 8,
      "trustScore": 7,
      "color": "#A78BFA"
    },
    {
      "id": "mu-fsc",
      "name": "Mauritius",
      "city": "Port Louis",
      "country": "Mauritius",
      "countryCode": "MU",
      "lat": -20.1609,
      "lng": 57.5012,
      "regulator": "Mauritius FSC",
      "brokerCount": 7,
      "avgRebatePerLot": 7,
      "trustScore": 8.2,
      "color": "#22D3EE"
    },
    {
      "id": "ky-cima",
      "name": "Cayman Islands",
      "city": "George Town",
      "country": "Cayman Islands",
      "countryCode": "KY",
      "lat": 19.3133,
      "lng": -81.2546,
      "regulator": "CIMA",
      "brokerCount": 11,
      "avgRebatePerLot": 7,
      "trustScore": 8.2,
      "color": "#22D3EE"
    },
    {
      "id": "bz-fsc",
      "name": "Belize",
      "city": "Belmopan",
      "country": "Belize",
      "countryCode": "BZ",
      "lat": 17.251,
      "lng": -88.759,
      "regulator": "FSC-BZ",
      "brokerCount": 0,
      "avgRebatePerLot": 8,
      "trustScore": 7,
      "color": "#A78BFA"
    },
    {
      "id": "pl-knf",
      "name": "Poland",
      "city": "Warsaw",
      "country": "Poland",
      "countryCode": "PL",
      "lat": 52.2297,
      "lng": 21.0122,
      "regulator": "KNF",
      "brokerCount": 2,
      "avgRebatePerLot": 6.1,
      "trustScore": 9.4,
      "color": "#4ADE80"
    },
    {
      "id": "ee-fi",
      "name": "Estonia",
      "city": "Tallinn",
      "country": "Estonia",
      "countryCode": "EE",
      "lat": 59.437,
      "lng": 24.7536,
      "regulator": "EFSA",
      "brokerCount": 1,
      "avgRebatePerLot": 6.1,
      "trustScore": 9.4,
      "color": "#4ADE80"
    },
    {
      "id": "vu-vfsc",
      "name": "Vanuatu",
      "city": "Port Vila",
      "country": "Vanuatu",
      "countryCode": "VU",
      "lat": -17.7333,
      "lng": 168.3273,
      "regulator": "VFSC",
      "brokerCount": 29,
      "avgRebatePerLot": 8,
      "trustScore": 7,
      "color": "#A78BFA"
    },
    {
      "id": "id-bap",
      "name": "Indonesia",
      "city": "Jakarta",
      "country": "Indonesia",
      "countryCode": "ID",
      "lat": -6.2088,
      "lng": 106.8456,
      "regulator": "Bappebti",
      "brokerCount": 2,
      "avgRebatePerLot": 7,
      "trustScore": 8.2,
      "color": "#22D3EE"
    },
    {
      "id": "ke-cma",
      "name": "Kenya",
      "city": "Nairobi",
      "country": "Kenya",
      "countryCode": "KE",
      "lat": -1.2921,
      "lng": 36.8219,
      "regulator": "Capital Markets Authority",
      "brokerCount": 3,
      "avgRebatePerLot": 7,
      "trustScore": 8.2,
      "color": "#22D3EE"
    },
    {
      "id": "my-lfsa",
      "name": "Malaysia (Labuan)",
      "city": "Labuan",
      "country": "Malaysia",
      "countryCode": "MY",
      "lat": 5.2831,
      "lng": 115.2308,
      "regulator": "Labuan Financial Services Authority",
      "brokerCount": 1,
      "avgRebatePerLot": 7,
      "trustScore": 8.2,
      "color": "#22D3EE"
    }
  ]
}